README.md
setup.py
force_kwargs/_README.py
force_kwargs/__init__.py
force_kwargs/_pickled.py
force_kwargs/templated_setup.py
force_kwargs.egg-info/PKG-INFO
force_kwargs.egg-info/SOURCES.txt
force_kwargs.egg-info/dependency_links.txt
force_kwargs.egg-info/top_level.txt