Metadata-Version: 2.1
Name: force_kwargs
Version: 0.101
Summary: A simple decorator to force kwargs. Doing so provides readability to the function signature.
Author: Joel Watson (matrikater)
